unidep/__init__.py
unidep/_cli.py
unidep/_conda_env.py
unidep/_conda_lock.py
unidep/_conflicts.py
unidep/_dependencies_parsing.py
unidep/_hatch_integration.py
unidep/_pytest_plugin.py
unidep/_setuptools_integration.py
unidep/_version.py
unidep/platform_definitions.py
unidep/py.typed
unidep/utils.py
unidep-2.0.0.dist-info/licenses/LICENSE
unidep-2.0.0.dist-info/METADATA
unidep-2.0.0.dist-info/WHEEL
unidep-2.0.0.dist-info/entry_points.txt
unidep-2.0.0.dist-info/top_level.txt
unidep-2.0.0.dist-info/RECORD
