Metadata-Version: 2.4
Name: unidep
Version: 2.0.0
Summary: Unified Conda and Pip requirements management.
Author-email: Bas Nijholt <bas@nijho.lt>
Project-URL: Homepage, https://github.com/basnijholt/unidep
Requires-Python: >=3.7
License-File: LICENSE
Requires-Dist: packaging
Requires-Dist: ruamel.yaml
Requires-Dist: typing_extensions; python_version < "3.8"
Requires-Dist: tomli; python_version < "3.11"
Provides-Extra: toml
Requires-Dist: tomli; python_version < "3.11" and extra == "toml"
Provides-Extra: conda-lock
Requires-Dist: conda-lock; extra == "conda-lock"
Requires-Dist: conda-package-handling; extra == "conda-lock"
Provides-Extra: pip-compile
Requires-Dist: pip-tools; extra == "pip-compile"
Provides-Extra: pytest
Requires-Dist: pytest; extra == "pytest"
Requires-Dist: GitPython; extra == "pytest"
Provides-Extra: rich
Requires-Dist: rich-argparse; extra == "rich"
Provides-Extra: all
Requires-Dist: unidep[conda-lock,pip-compile,pytest,rich,toml]; extra == "all"
Provides-Extra: docs
Requires-Dist: myst-parser; extra == "docs"
Requires-Dist: sphinx; extra == "docs"
Requires-Dist: furo; extra == "docs"
Requires-Dist: emoji; extra == "docs"
Requires-Dist: sphinx-autodoc-typehints; extra == "docs"
Provides-Extra: test
Requires-Dist: unidep[all]; extra == "test"
Requires-Dist: tomli_w; extra == "test"
Requires-Dist: pytest; extra == "test"
Requires-Dist: pre-commit; extra == "test"
Requires-Dist: coverage; extra == "test"
Requires-Dist: pytest-cov; extra == "test"
Requires-Dist: pytest-mock; extra == "test"
Requires-Dist: conda-package-handling; extra == "test"
Requires-Dist: rich; extra == "test"
Dynamic: license-file
